
{
    "data":[
        {
            "SHIPMENT_ID":"9998",
            "SHIPMENT_TYPE_ID":"SALES_SHIPMENT",
            "STATUS_ID":"SHIPMENT_INPUT",
            "PRIMARY_ORDER_ID":"DEMO10090",
            "PRIMARY_RETURN_ID":"",
            "PRIMARY_SHIP_GROUP_SEQ_ID":"00001",
            "PICKLIST_BIN_ID":"",
            "ESTIMATED_READY_DATE":"",
            "ESTIMATED_SHIP_DATE":"",
            "ESTIMATED_SHIP_WORK_EFF_ID":"",
            "ESTIMATED_ARRIVAL_DATE":"",
            "ESTIMATED_ARRIVAL_WORK_EFF_ID":"",
            "LATEST_CANCEL_DATE":"",
            "ESTIMATED_SHIP_COST":12.45,
            "CURRENCY_UOM_ID":"",
            "HANDLING_INSTRUCTIONS":"",
            "ORIGIN_FACILITY_ID":"WebStoreWarehouse",
            "DESTINATION_FACILITY_ID":"",
            "ORIGIN_CONTACT_MECH_ID":"9200",
            "ORIGIN_TELECOM_NUMBER_ID":"9201",
            "DESTINATION_CONTACT_MECH_ID":"9015",
            "DESTINATION_TELECOM_NUMBER_ID":"9025",
            "PARTY_ID_TO":"DemoCustomer",
            "PARTY_ID_FROM":"",
            "ADDITIONAL_SHIPPING_CHARGE":"",
            "ADDTL_SHIPPING_CHARGE_DESC":"",
            "CREATED_DATE":"2008-06-10 12:59:26.8",
            "CREATED_BY_USER_LOGIN":"",
            "LAST_MODIFIED_DATE":"",
            "LAST_MODIFIED_BY_USER_LOGIN":"",
            "LAST_UPDATED_STAMP":"2023-06-24 20:01:03.913",
            "LAST_UPDATED_TX_STAMP":"2023-06-24 20:00:59.252",
            "CREATED_STAMP":"2023-06-24 20:01:03.913",
            "CREATED_TX_STAMP":"2023-06-24 20:00:59.252"
        },
        {
            "SHIPMENT_ID":"9999",
            "SHIPMENT_TYPE_ID":"PURCHASE_SHIPMENT",
            "STATUS_ID":"PURCH_SHIP_CREATED",
            "PRIMARY_ORDER_ID":"DEMO10091",
            "PRIMARY_RETURN_ID":"",
            "PRIMARY_SHIP_GROUP_SEQ_ID":"00001",
            "PICKLIST_BIN_ID":"",
            "ESTIMATED_READY_DATE":"",
            "ESTIMATED_SHIP_DATE":"",
            "ESTIMATED_SHIP_WORK_EFF_ID":"",
            "ESTIMATED_ARRIVAL_DATE":"",
            "ESTIMATED_ARRIVAL_WORK_EFF_ID":"",
            "LATEST_CANCEL_DATE":"",
            "ESTIMATED_SHIP_COST":"",
            "CURRENCY_UOM_ID":"",
            "HANDLING_INSTRUCTIONS":"",
            "ORIGIN_FACILITY_ID":"",
            "DESTINATION_FACILITY_ID":"",
            "ORIGIN_CONTACT_MECH_ID":"",
            "ORIGIN_TELECOM_NUMBER_ID":"",
            "DESTINATION_CONTACT_MECH_ID":"",
            "DESTINATION_TELECOM_NUMBER_ID":"",
            "PARTY_ID_TO":"",
            "PARTY_ID_FROM":"",
            "ADDITIONAL_SHIPPING_CHARGE":"",
            "ADDTL_SHIPPING_CHARGE_DESC":"",
            "CREATED_DATE":"2008-06-10 12:59:26.8",
            "CREATED_BY_USER_LOGIN":"",
            "LAST_MODIFIED_DATE":"",
            "LAST_MODIFIED_BY_USER_LOGIN":"",
            "LAST_UPDATED_STAMP":"2023-06-24 20:01:03.968",
            "LAST_UPDATED_TX_STAMP":"2023-06-24 20:00:59.252",
            "CREATED_STAMP":"2023-06-24 20:01:03.968",
            "CREATED_TX_STAMP":"2023-06-24 20:00:59.252"
        },
        {
            "SHIPMENT_ID":"9997",
            "SHIPMENT_TYPE_ID":"PURCHASE_SHIPMENT",
            "STATUS_ID":"PURCH_SHIP_RECEIVED",
            "PRIMARY_ORDER_ID":"Demo1001",
            "PRIMARY_RETURN_ID":"",
            "PRIMARY_SHIP_GROUP_SEQ_ID":"00001",
            "PICKLIST_BIN_ID":"",
            "ESTIMATED_READY_DATE":"",
            "ESTIMATED_SHIP_DATE":"",
            "ESTIMATED_SHIP_WORK_EFF_ID":"",
            "ESTIMATED_ARRIVAL_DATE":"",
            "ESTIMATED_ARRIVAL_WORK_EFF_ID":"",
            "LATEST_CANCEL_DATE":"",
            "ESTIMATED_SHIP_COST":0.0,
            "CURRENCY_UOM_ID":"",
            "HANDLING_INSTRUCTIONS":"",
            "ORIGIN_FACILITY_ID":"",
            "DESTINATION_FACILITY_ID":"WebStoreWarehouse",
            "ORIGIN_CONTACT_MECH_ID":"",
            "ORIGIN_TELECOM_NUMBER_ID":"",
            "DESTINATION_CONTACT_MECH_ID":"9200",
            "DESTINATION_TELECOM_NUMBER_ID":"9201",
            "PARTY_ID_TO":"",
            "PARTY_ID_FROM":"DemoSupplier",
            "ADDITIONAL_SHIPPING_CHARGE":"",
            "ADDTL_SHIPPING_CHARGE_DESC":"",
            "CREATED_DATE":"2008-06-10 12:59:26.8",
            "CREATED_BY_USER_LOGIN":"",
            "LAST_MODIFIED_DATE":"",
            "LAST_MODIFIED_BY_USER_LOGIN":"",
            "LAST_UPDATED_STAMP":"2023-06-24 20:01:04.019",
            "LAST_UPDATED_TX_STAMP":"2023-06-24 20:00:59.252",
            "CREATED_STAMP":"2023-06-24 20:01:04.019",
            "CREATED_TX_STAMP":"2023-06-24 20:00:59.252"
        },
        {
            "SHIPMENT_ID":"9996",
            "SHIPMENT_TYPE_ID":"SALES_SHIPMENT",
            "STATUS_ID":"SHIPMENT_SHIPPED",
            "PRIMARY_ORDER_ID":"Demo1002",
            "PRIMARY_RETURN_ID":"",
            "PRIMARY_SHIP_GROUP_SEQ_ID":"00001",
            "PICKLIST_BIN_ID":"",
            "ESTIMATED_READY_DATE":"",
            "ESTIMATED_SHIP_DATE":"",
            "ESTIMATED_SHIP_WORK_EFF_ID":"",
            "ESTIMATED_ARRIVAL_DATE":"",
            "ESTIMATED_ARRIVAL_WORK_EFF_ID":"",
            "LATEST_CANCEL_DATE":"",
            "ESTIMATED_SHIP_COST":12.1,
            "CURRENCY_UOM_ID":"",
            "HANDLING_INSTRUCTIONS":"",
            "ORIGIN_FACILITY_ID":"WebStoreWarehouse",
            "DESTINATION_FACILITY_ID":"",
            "ORIGIN_CONTACT_MECH_ID":"9200",
            "ORIGIN_TELECOM_NUMBER_ID":"9201",
            "DESTINATION_CONTACT_MECH_ID":"9015",
            "DESTINATION_TELECOM_NUMBER_ID":"9025",
            "PARTY_ID_TO":"DemoCustomer",
            "PARTY_ID_FROM":"Company",
            "ADDITIONAL_SHIPPING_CHARGE":"",
            "ADDTL_SHIPPING_CHARGE_DESC":"",
            "CREATED_DATE":"2009-08-17 14:56:57.553",
            "CREATED_BY_USER_LOGIN":"",
            "LAST_MODIFIED_DATE":"",
            "LAST_MODIFIED_BY_USER_LOGIN":"",
            "LAST_UPDATED_STAMP":"2023-06-24 20:01:04.306",
            "LAST_UPDATED_TX_STAMP":"2023-06-24 20:00:59.252",
            "CREATED_STAMP":"2023-06-24 20:01:04.306",
            "CREATED_TX_STAMP":"2023-06-24 20:00:59.252"
        }
    ]
}